database_knotinfo/__init__.py
database_knotinfo/__version__.py
database_knotinfo/csv_data/knotinfo_data_complete.csv
database_knotinfo/csv_data/linkinfo_data_complete.csv
database_knotinfo-2025.10.1.dist-info/licenses/LICENSE
database_knotinfo-2025.10.1.dist-info/METADATA
database_knotinfo-2025.10.1.dist-info/WHEEL
database_knotinfo-2025.10.1.dist-info/top_level.txt
database_knotinfo-2025.10.1.dist-info/RECORD
