Metadata-Version: 2.4
Name: database_knotinfo
Version: 2025.10.1
Summary: The KnotInfo and LinkInfo databases as lists of dictionaries
Home-page: https://github.com/soehms/database_knotinfo
Author: Sebastian Oehms
Author-email: seb.oehms@gmail.com
License: GPL
Keywords: KnotInfo,LinkInfo,SageMath,database,knot,link,mathematics,topology,invariants
Classifier: Development Status :: 5 - Production/Stable
Classifier: Programming Language :: Python :: 3
License-File: LICENSE
Dynamic: author
Dynamic: author-email
Dynamic: classifier
Dynamic: description
Dynamic: description-content-type
Dynamic: home-page
Dynamic: keywords
Dynamic: license
Dynamic: license-file
Dynamic: summary
